Metadata-Version: 2.1
Name: notion-dashworks
Version: 0.0.28
Summary: Unofficial Python API client for Notion.so
Home-page: https://github.com/dashworkstech/notion-py
Author: Dashworks
Author-email: support@dashworks.ai
License: UNKNOWN
Platform: UNKNOWN
Classifier: Programming Language :: Python :: 3
Classifier: License :: OSI Approved :: MIT License
Classifier: Operating System :: OS Independent
Requires-Python: >=3.7
Requires-Dist: requests
Requires-Dist: commonmark
Requires-Dist: bs4
Requires-Dist: tzlocal
Requires-Dist: python-slugify
Requires-Dist: dictdiffer
Requires-Dist: cached-property
